dict/__init__.py
dict_cli-1.3.4.dist-info/DESCRIPTION.rst
dict_cli-1.3.4.dist-info/METADATA
dict_cli-1.3.4.dist-info/RECORD
dict_cli-1.3.4.dist-info/WHEEL
dict_cli-1.3.4.dist-info/entry_points.txt
dict_cli-1.3.4.dist-info/metadata.json
dict_cli-1.3.4.dist-info/top_level.txt
