Metadata-Version: 2.0
Name: dict-cli
Version: 1.3.4
Summary: 命令行下中英文翻译工具（Chinese and English translation tools in the command line）
Home-page: https://github.com/wufeifei/dict
Author: Feei
Author-email: feei@feei.cn
License: MIT
Keywords: Translation English2Chinese Chinese2English Command-line
Platform: any
Classifier: Development Status :: 5 - Production/Stable
Classifier: Intended Audience :: Developers
Classifier: Natural Language :: Chinese (Simplified)
Classifier: Natural Language :: English
Classifier: Topic :: Utilities
Classifier: Topic :: Terminals
Classifier: Topic :: System :: Distributed Computing
Classifier: License :: OSI Approved :: MIT License
Classifier: Programming Language :: Python :: 2
Classifier: Programming Language :: Python :: 2.7
Classifier: Programming Language :: Python :: 3
Classifier: Programming Language :: Python :: 3.3
Classifier: Programming Language :: Python :: 3.4
Classifier: Programming Language :: Python :: 3.5
